danmakuC-0.3.6.dist-info/RECORD
danmakuC-0.3.6.dist-info/LICENSE
danmakuC-0.3.6.dist-info/WHEEL
danmakuC-0.3.6.dist-info/entry_points.txt
danmakuC-0.3.6.dist-info/top_level.txt
danmakuC-0.3.6.dist-info/METADATA
danmakuC/__init__.py
danmakuC/__version__.py
danmakuC/ass.pyi
danmakuC/bilibili.py
danmakuC/niconico.py
danmakuC/ass.cpython-311-darwin.so
danmakuC/__main__.py
danmakuC/protobuf/__init__.py
danmakuC/protobuf/bilibili/__init__.py
danmakuC/protobuf/bilibili/reply_pb2.py
danmakuC/protobuf/bilibili/view_pb2.py
danmakuC/protobuf/niconico/nndcomment_pb2.py
danmakuC/protobuf/niconico/__init__.py
