Metadata-Version: 2.1
Name: danmakuC
Version: 0.3.6
Summary: Faster conversion for larger Danmaku to Ass format
Author: HFrost0, m13253, Nyakku Shigure
License: GPLv3
Classifier: Programming Language :: C++
Classifier: Programming Language :: Python :: 3
Classifier: Programming Language :: Python :: 3.8
Classifier: Programming Language :: Python :: 3.9
Classifier: Programming Language :: Python :: 3.10
Classifier: Programming Language :: Python :: 3.11
Classifier: Programming Language :: Python :: 3 :: Only
Requires-Python: >=3.8.3
License-File: LICENSE
Requires-Dist: protobuf (>=4.21.0)
